[
    {
        "id": "ascended_dragonheart_hero_skill_normal",
        "description": "Tome of Dragons"
    },
    {
        "id": "ascended_mistborne_hero_skill_normal",
        "description": "Tome of Fey Mists"
    },
    {
        "id": "ascended_stormbearer_hero_skill_normal",
        "description": "Tome of the Stormborne"
    },
    {
        "id": "ascended_disruptor_hero_skill_normal",
        "description": "Tome of Severing"
    },
    {
        "id": "ascended_golemheart_hero_skill_normal",
        "description": "Tome of the Construct"
    },
    {
        "id": "ascended_artillerist_hero_skill_normal",
        "description": "Tome of the Dreadnought"
    },
    {
        "id": "ascended_alchemist_hero_skill_normal",
        "description": "Tome of Alchemy"
    },
    {
        "id": "ascended_shaper_hero_skill_normal",
        "description": "Tome of Evolution"
    },
    {
        "id": "ascended_spiritbreaker_hero_skill_normal",
        "description": "Tome of the Doomherald, Tome of Oblivion"
    },
    {
        "id": "ascended_deathcaller_hero_skill_normal",
        "description": "Tome of Souls, Tome of Necromancy, Tome of the Great Transformation, Tome of the Reaper"
    },
    {
        "id": "ascended_cryomancer_hero_skill_normal",
        "description": "Tome of Cryomancy, Tome of Cold Dark"
    },
    {
        "id": "ascended_hunter_hero_skill_normal",
        "description": "Tome of Beasts, Tome of Vigor"
    },
    {
        "id": "ascended_rootwarden_hero_skill_normal",
        "description": "Tome of Roots,  Tome of Fertility,Tome of Glades, Tome of Nature's Wrath, Tome of Cycles,Tome of Paradise"
    },
    {
        "id": "ascended_restorer_hero_skill_normal",
        "description": "Tome of the Goddess of Nature"
    },
    {
        "id": "ascended_artificer_hero_skill_normal",
        "description": "Tome of Artificing, Tome of Enchantment, Tome of the Golden Realm"
    },
    {
        "id": "ascended_earthshaker_hero_skill_normal",
        "description": "Tome of Rock, Tome of Terramancy, Tome of Winds,Tome of the Crucible, Tome of Geomancy"
    },
    {
        "id": "ascended_forgemaster_hero_skill_normal",
        "description": "Tome of the Creator"
    },
    {
        "id": "ascended_seer_hero_skill_normal",
        "description": "Tome of Scrying, Tome of Evocation, Tome of Teleportation, Tome of Amplification, Tome of Astral Convergence"
    },
    {
        "id": "ascended_summoner_hero_skill_normal",
        "description": "Tome of Warding, Tome of Summoning, Tome of the Astral Mirror"
    },
    {
        "id": "ascended_sorcerer_hero_skill_normal",
        "description": "Tome of the Archmage"
    },
    {
        "id": "ascended_occultist_hero_skill_normal",
        "description": "Tome of Mayhem, Tome of Pandemonium, Tome of the Demon Gate"
    },
    {
        "id": "ascended_pyromancer_hero_skill_normal",
        "description": "Tome of Pyromancer, Tome of Chaos Channeling"
    },
    {
        "id": "ascended_warlord_hero_skill_normal",
        "description": "Tome of the Horde, Tome of Devastation, Tome of Revelry, Tome of the Chaos Lord"
    },
    {
        "id": "ascended_subjugator_hero_skill_normal",
        "description": "Tome of Zeal, Tome of Subjugation, Tome of the Inquisition, Tome of Supremacy"
    },
    {
        "id": "ascended_prophet_hero_skill_normal",
        "description": "Tome of Faith, Tome of Beacon, Tome of Sanctuary, Tome of Exaltation"
    },
    {
        "id": "ascended_martyr_hero_skill_normal",
        "description": "Tome of the God Emperor"
    },
    {
        "id": "ascended_deepcaller_hero_skill_normal",
        "description": "Tome of the Tentacle"
    },
    {
        "id": "ascended_pyrebearer_hero_skill_normal",
        "description": "Tome of the Cleansing Flame"
    },
    {
        "id": "ascended_shadowshaper_hero_skill_normal",
        "description": "Tome of Corruption",
        "extraspell": "summon_willthief"
    },
    {
        "id": "ascended_master_hero_skill_normal",
        "description": "Tome of Discipline"
    },
    {
        "id": "ascended_assassin_hero_skill_normal",
        "description": "Tome of Shades"
    },
    {
        "id": "ascended_blessbringer_hero_skill_normal",
        "description": "Tome of Prosperity",
        "extraspell": "summon_blessed_dragon"
    },
    {
        "id": "ascended_desecrator_hero_skill_normal",
        "description": "Tome of Calamity",
        "extraspell": "summon_accursed_ogre"
    },
    {
        "id": "ascended_dungeon_keeper_hero_skill_normal",
        "description": "Tome of Dungeon Depths",
       
    }
]
